infi.pypi_manager-0.4.45-py3.7-nspkg.pth
infi/pypi_manager/__init__.py
infi/pypi_manager/__version__.py
infi/pypi_manager/depends/__init__.py
infi/pypi_manager/depends/dependencies.py
infi/pypi_manager/depends/licenses.py
infi/pypi_manager/depends/recursive.py
infi/pypi_manager/mirror/__init__.py
infi/pypi_manager/mirror/mirror_all.py
infi/pypi_manager/mirror/mirror_build.py
infi/pypi_manager/mirror/mirror_package.py
infi/pypi_manager/mirror/rebuild_package.py
infi/pypi_manager/scripts/__init__.py
infi/pypi_manager/scripts/compare_pypi_repos.py
infi/pypi_manager/scripts/hard_install.py
infi/pypi_manager/scripts/skipped_packages.txt
infi/pypi_manager/tests/__init__.py
infi.pypi_manager-0.4.45.dist-info/LICENSE
infi.pypi_manager-0.4.45.dist-info/METADATA
infi.pypi_manager-0.4.45.dist-info/WHEEL
infi.pypi_manager-0.4.45.dist-info/entry_points.txt
infi.pypi_manager-0.4.45.dist-info/namespace_packages.txt
infi.pypi_manager-0.4.45.dist-info/top_level.txt
infi.pypi_manager-0.4.45.dist-info/RECORD
