Metadata-Version: 2.1
Name: infi.pypi-manager
Version: 0.4.45
Summary: mirror distributions from pypi.python.org to our local djangopypi server
Home-page: https://github.com/Infinidat/infi.pypi_manager
Author: Arnon Yaari
Author-email: arnony@infinidat.com
License: BSD
Platform: UNKNOWN
Classifier: Intended Audience :: Developers
Classifier: Intended Audience :: System Administrators
Classifier: License :: OSI Approved :: BSD License
Classifier: Operating System :: OS Independent
Classifier: Programming Language :: Python
Classifier: Programming Language :: Python :: 2
Classifier: Programming Language :: Python :: 3
Classifier: Topic :: Software Development :: Libraries :: Python Modules
Requires-Dist: docopt
Requires-Dist: infi.execute
Requires-Dist: infi.pyutils
Requires-Dist: PrettyTable
Requires-Dist: requests
Requires-Dist: setuptools
Requires-Dist: six
